rch/__init__.py
rch/arrays.py
rch/df.py
rch/gdf.py
rch/gis.py
rch/hydro.py
rch/sudoku.py
rch/web.py
rch-0.15.dist-info/LICENSE
rch-0.15.dist-info/METADATA
rch-0.15.dist-info/WHEEL
rch-0.15.dist-info/top_level.txt
rch-0.15.dist-info/RECORD
