Metadata-Version: 2.1
Name: rch
Version: 0.15
Summary: A package containing the personal python utilities of Riley Hales
Home-page: https://rileyhales.com
Author: Riley Hales
Author-email: rchales@byu.edu
License: BSD 3-Clause Clear License
Project-URL: Source, https://github.com/rileyhales/pyrch
Project-URL: License, https://choosealicense.com/licenses/bsd-3-clause-clear
Classifier: Programming Language :: Python :: 3
Classifier: Topic :: Scientific/Engineering
Classifier: Intended Audience :: Science/Research
Classifier: License :: OSI Approved :: BSD License
Classifier: Natural Language :: English
Requires-Python: >=3.11
License-File: LICENSE
Requires-Dist: google-api-python-client
Requires-Dist: google-auth-httplib2
Requires-Dist: google-auth-oauthlib
Requires-Dist: affine
Requires-Dist: numpy
Requires-Dist: pandas
Requires-Dist: geopandas
Requires-Dist: requests
Requires-Dist: shapely
Requires-Dist: rasterio
